{
    "1": {
        "nome": "Gustavo",
        "endere\u00e7o": "Bjl",
        "telefone": [
            "(00)0000-0000"
        ]
    },
    "2": {
        "nome": "Rita",
        "endere\u00e7o": "Bjl",
        "telefone": [
            "(11)1111-1211"
        ]
    },
    "3": {
        "nome": "Deri",
        "endere\u00e7o": "Projeto",
        "telefone": [
            "(88)8888-8888"
        ]
    },
    "4": {
        "nome": "Ana",
        "endere\u00e7o": "33",
        "telefone": [
            "(99)9999-9999"
        ]
    }
}